MANIFEST.in
README.txt
setup.py
cms_draggable_files/__init__.py
cms_draggable_files/forms.py
cms_draggable_files/models.py
cms_draggable_files/urls.py
cms_draggable_files/views.py
cms_draggable_files.egg-info/PKG-INFO
cms_draggable_files.egg-info/SOURCES.txt
cms_draggable_files.egg-info/dependency_links.txt
cms_draggable_files.egg-info/top_level.txt