Metadata-Version: 1.0
Name: cms-draggable-files
Version: 0.1.6
Summary: CMS placeholder can recieve dragged files and add to plugin by files extensions.
Home-page: https://github.com/jelenak/cms-draggable-files
Author: Jelena Kutalovskaja
Author-email: jelena.kutalovskaja@gmail.com
License: LICENSE.txt
Platform: UNKNOWN
